sergeant/__init__.py
sergeant/broker.py
sergeant/config.py
sergeant/connector/__init__.py
sergeant/connector/_connector.py
sergeant/connector/local.py
sergeant/connector/mongo.py
sergeant/connector/redis.py
sergeant/encoder/__init__.py
sergeant/encoder/compressor/__init__.py
sergeant/encoder/compressor/_compressor.py
sergeant/encoder/compressor/bzip2.py
sergeant/encoder/compressor/gzip.py
sergeant/encoder/compressor/lzma.py
sergeant/encoder/compressor/zlib.py
sergeant/encoder/encoder.py
sergeant/encoder/serializer/__init__.py
sergeant/encoder/serializer/_serializer.py
sergeant/encoder/serializer/msgpack.py
sergeant/encoder/serializer/pickle.py
sergeant/executor/__init__.py
sergeant/executor/_executor.py
sergeant/executor/serial.py
sergeant/executor/threaded.py
sergeant/killer/__init__.py
sergeant/killer/process.py
sergeant/killer/thread.py
sergeant/logging/__init__.py
sergeant/logging/logstash.py
sergeant/objects.py
sergeant/py.typed
sergeant/slave.py
sergeant/supervisor.py
sergeant/worker.py
sergeant-0.27.0.dist-info/LICENSE
sergeant-0.27.0.dist-info/METADATA
sergeant-0.27.0.dist-info/WHEEL
sergeant-0.27.0.dist-info/RECORD
