Metadata-Version: 2.3
Name: sergeant
Version: 0.27.0
Summary: Fast, Safe & Simple Asynchronous Task Queues Written In Pure Python
License: MIT
Keywords: tasks,worker,queue,redis,celery
Author: Gal Ben David
Author-email: gal@intsights.com
Requires-Python: >=3.7,<4.0
Classifier: License :: OSI Approved :: MIT License
Classifier: Programming Language :: Python :: 3
Classifier: Programming Language :: Python :: 3.7
Classifier: Programming Language :: Python :: 3.8
Classifier: Programming Language :: Python :: 3.9
Classifier: Programming Language :: Python :: 3.10
Classifier: Programming Language :: Python :: 3.11
Classifier: Programming Language :: Python :: 3.12
Classifier: Programming Language :: Python :: 3.13
Requires-Dist: hiredis (>=2,<3)
Requires-Dist: msgpack (>=1,<2)
Requires-Dist: orjson (>=3,<4)
Requires-Dist: psutil (>=5,<6)
Requires-Dist: pymongo (>=3.0,<5.0)
Requires-Dist: redis (>=4,<5)
Requires-Dist: typing_extensions (>=4,<5)
Project-URL: Documentation, https://intsights.github.io/sergeant/
Project-URL: Homepage, https://github.com/Intsights/sergeant
Project-URL: Repository, https://github.com/Intsights/sergeant
